pywslpath/__init__.py
pywslpath/pywslpath.py
pywslpath-0.3.2.dist-info/LICENSE
pywslpath-0.3.2.dist-info/METADATA
pywslpath-0.3.2.dist-info/WHEEL
pywslpath-0.3.2.dist-info/entry_points.txt
pywslpath-0.3.2.dist-info/top_level.txt
pywslpath-0.3.2.dist-info/RECORD
