Metadata-Version: 2.1
Name: pywslpath
Version: 0.3.2
Summary: Converts Unix and Windows format paths in WSL
Home-page: https://github.com/riag/pywslpath
Author: riag
Author-email: riag@163.com
License: Apache
Platform: linux
Classifier: Programming Language :: Python :: 3
Requires-Dist: click (>=7.0)
